acuitylib/VERSION
acuitylib/__init__.py
acuitylib/acuity_runtime.cpython-310-x86_64-linux-gnu.so
acuitylib/acuity_runtime_utils.cpython-310-x86_64-linux-gnu.so
acuitylib/acuity_smart_graph.cpython-310-x86_64-linux-gnu.so
acuitylib/acuityerror.cpython-310-x86_64-linux-gnu.so
acuitylib/acuitylog.cpython-310-x86_64-linux-gnu.so
acuitylib/acuitynet.cpython-310-x86_64-linux-gnu.so
acuitylib/acuitynetbuilder.cpython-310-x86_64-linux-gnu.so
acuitylib/client.cpython-310-x86_64-linux-gnu.so
acuitylib/custom_interface.cpython-310-x86_64-linux-gnu.so
acuitylib/enum.cpython-310-x86_64-linux-gnu.so
acuitylib/file_mode.cpython-310-x86_64-linux-gnu.so
acuitylib/inference_session.cpython-310-x86_64-linux-gnu.so
acuitylib/initializers.cpython-310-x86_64-linux-gnu.so
acuitylib/json_encoder.cpython-310-x86_64-linux-gnu.so
acuitylib/net_helper.cpython-310-x86_64-linux-gnu.so
acuitylib/net_input_meta.cpython-310-x86_64-linux-gnu.so
acuitylib/net_output_meta.cpython-310-x86_64-linux-gnu.so
acuitylib/netwalker.cpython-310-x86_64-linux-gnu.so
acuitylib/parallel_executor.cpython-310-x86_64-linux-gnu.so
acuitylib/pytorch_art.cpython-310-x86_64-linux-gnu.so
acuitylib/runtime_config.cpython-310-x86_64-linux-gnu.so
acuitylib/tensor_manager.cpython-310-x86_64-linux-gnu.so
acuitylib/utils.cpython-310-x86_64-linux-gnu.so
acuitylib/vsi_nn.cpython-310-x86_64-linux-gnu.so
acuitylib/vsi_sdk.tar.gz
acuitylib/vsi_zsp.cpython-310-x86_64-linux-gnu.so
acuitylib/vsinn_utils.cpython-310-x86_64-linux-gnu.so
acuitylib/xtf.cpython-310-x86_64-linux-gnu.so
acuitylib/yaml_parser.cpython-310-x86_64-linux-gnu.so
acuitylib/zsp_net_helper.cpython-310-x86_64-linux-gnu.so
acuitylib/app/__init__.py
acuitylib/app/utils.cpython-310-x86_64-linux-gnu.so
acuitylib/app/console/__init__.py
acuitylib/app/console/commands.cpython-310-x86_64-linux-gnu.so
acuitylib/app/console/fake_data.cpython-310-x86_64-linux-gnu.so
acuitylib/app/console/inputmeta.cpython-310-x86_64-linux-gnu.so
acuitylite-6.51.0.dist-info/METADATA
acuitylite-6.51.0.dist-info/WHEEL
acuitylite-6.51.0.dist-info/top_level.txt
acuitylite-6.51.0.dist-info/RECORD
