Metadata-Version: 2.1
Name: acuitylite
Version: 6.51.0
Summary: UNKNOWN
Home-page: UNKNOWN
Author: Verisilicon
Author-email: ML_Support@verisilicon.com
License: UNKNOWN
Platform: UNKNOWN
Requires-Dist: dill (==0.2.8.2)
Requires-Dist: networkx (==3.3)
Requires-Dist: numpy (==1.26.4)
Requires-Dist: onnx (==1.16.2)
Requires-Dist: onnxoptimizer (==0.3.13)
Requires-Dist: ply (==3.11)
Requires-Dist: protobuf (==3.20.3)
Requires-Dist: ruamel.yaml (==0.17.40)
Requires-Dist: scipy (==1.14.1)
Requires-Dist: tensorflow (==2.17.0)
